{
  "date": "2020.03.08 - 2020.12.06",
  "datetime": "2020/12/06 10:30:00",
  "description": "at BnA Alter Museum",
  "youtube": [
    {
      "title": "3月8日",
      "id": "AnqKtwk7mKU"
    },
    {
      "title": "4月5日",
      "id": "bVyJ3xpF9jI"
    },
    {
      "title": "5月3日",
      "id": "YrDo1Zg2avg"
    },
    {
      "title": "6月7日",
      "id": "LfpdOdqrqSI"
    },
    {
      "title": "7月5日",
      "id": "YcO45vs8_Tc"
    },
    {
      "title": "8月2日",
      "id": "MQsOJ9NNrho"
    },
    {
      "title": "9月6日",
      "id": "4iRCoFB2qZw"
    },
    {
      "title": "10月4日",
      "id": "LPlODq-ZKTE"
    },
    {
      "title": "11月1日",
      "id": "7UI5u-suxig"
    },
    {
      "title": "12月6日",
      "id": "Ur2Yxipmg5w"
    }
  ]
}