{
  "title" : "プレイタイムズ",
  "description" : "a place of pray/play for us",
  "author" : "∧° ┐ | creative, community space",
  "src" : "/img/play/001.JPG",

  "images" : [
    {
      "img" : "play/001.JPG",
      "info" : [
        "Infomation",
        "More"
      ]
    },
    {
      "img" : "play/002.JPG",
      "info" : [
        "Infomation",
        "More"
      ]
    },
    {
      "img" : "play/003.JPG",
      "info" : [
        "Infomation",
        "More"
      ]
    },
    {
      "img" : "play/004.JPG",
      "info" : [
        "Infomation",
        "More"
      ]
    },
    {
      "img" : "play/005.JPG",
      "info" : [
        "Infomation",
        "More"
      ]
    },
    {
      "img" : "play/006.JPG",
      "info" : [
        "Infomation",
        "More"
      ]
    },
    {
      "img" : "play/007.JPG",
      "info" : [
        "Infomation",
        "More"
      ]
    },
    {
      "img" : "play/008.JPG",
      "info" : [
        "Infomation",
        "More"
      ]
    },
    {
      "img" : "play/009.JPG",
      "info" : [
        "Infomation",
        "More"
      ]
    },
    {
      "img" : "play/010.JPG",
      "info" : [
        "Infomation",
        "More"
      ]
    },
    {
      "img" : "play/011.JPG",
      "info" : [
        "Infomation",
        "More"
      ]
    },
    {
      "img" : "play/012.JPG",
      "info" : [
        "Infomation",
        "More"
      ]
    },
    {
      "img" : "play/013.JPG",
      "info" : [
        "Infomation",
        "More"
      ]
    },
    {
      "img" : "play/014.JPG",
      "info" : [
        "Infomation",
        "More"
      ]
    },
    {
      "img" : "play/015.JPG",
      "info" : [
        "Infomation",
        "More"
      ]
    },
    {
      "img" : "play/016.JPG",
      "info" : [
        "Infomation",
        "More"
      ]
    },
    {
      "img" : "play/017.JPG",
      "info" : [
        "Infomation",
        "More"
      ]
    },
    {
      "img" : "play/018.JPG",
      "info" : [
        "Infomation",
        "More"
      ]
    }
  ]
}
